[{"id":1,"service_id":3,"local_id":1,"chef_id":43,"name":"1ère Subdivision de la Fiscalité des Personnes Morales"},{"id":2,"service_id":3,"local_id":1,"chef_id":44,"name":"2ème Subdivision la Fiscalité des Personnes Morales"},{"id":3,"service_id":3,"local_id":1,"chef_id":45,"name":"3ème Subdivision la Fiscalité des Personnes Morales"},{"id":4,"service_id":3,"local_id":6,"chef_id":46,"name":"Subdivision Polyvalente d'EI Kelaa des Sraghnas"},{"id":5,"service_id":3,"local_id":4,"chef_id":47,"name":"Subdivision Polyvalente de Rehamna"},{"id":6,"service_id":5,"local_id":2,"chef_id":48,"name":"Subdivision de la Fiscalité des Professionnels - Gueliz Targa"},{"id":7,"service_id":5,"local_id":2,"chef_id":49,"name":"Subdivision de la Fiscalité des Professionnels - Médina Sidi Youssef Ben Ali"},{"id":8,"service_id":5,"local_id":2,"chef_id":50,"name":"Subdivision de la Fiscalité des Profession nels - Hay Mohammadi"},{"id":9,"service_id":5,"local_id":3,"chef_id":51,"name":"Subdivision Polyvalente d'EI Haouz"},{"id":10,"service_id":5,"local_id":5,"chef_id":52,"name":"Subdivision Polyvalente de Chichaoua"},{"id":11,"service_id":4,"local_id":1,"chef_id":53,"name":"Subdivision de la Fiscalité des Particuliers - Hay Mohammadi Gueliz Targa"},{"id":12,"service_id":4,"local_id":1,"chef_id":54,"name":"Subdivision de la Fiscatité des Particuliers - Medina Sidi Youssef Ben Ali"},{"id":13,"service_id":4,"local_id":1,"chef_id":55,"name":"Subdivision Polyvalente d'Essaouira"},{"id":14,"service_id":6,"local_id":9,"chef_id":56,"name":"Subdivision de la Fiscalité des Personnes Morales et des Professionnels de Safi"},{"id":15,"service_id":6,"local_id":9,"chef_id":57,"name":"Subdivision de la Fiscalité des Particuliers de Safi"},{"id":16,"service_id":6,"local_id":10,"chef_id":58,"name":"Subdivision Polyvalente de Youssoufia"}]